vdk_jupyterlab_extension/__init__.py
vdk_jupyterlab_extension/_version.py
vdk_jupyterlab_extension/config.py
vdk_jupyterlab_extension/convert_job.py
vdk_jupyterlab_extension/handlers.py
vdk_jupyterlab_extension/job_data.py
vdk_jupyterlab_extension/jupyter_notebook.py
vdk_jupyterlab_extension/oauth2.py
vdk_jupyterlab_extension/vdk_ui.py
vdk_jupyterlab_extension/jupyter_sample_job/10_notebook.ipynb
vdk_jupyterlab_extension/jupyter_sample_job/README.md
vdk_jupyterlab_extension/jupyter_sample_job/config.ini
vdk_jupyterlab_extension/jupyter_sample_job/requirements.txt
vdk_jupyterlab_extension/tests/__init__.py
vdk_jupyterlab_extension/tests/create_deployment_test.py
vdk_jupyterlab_extension/tests/test_convert_job_directory_processor.py
vdk_jupyterlab_extension/tests/test_directory_archiver.py
vdk_jupyterlab_extension/tests/test_oauth2.py
vdk_jupyterlab_extension/tests/test_remove_cell_outputs.py
vdk_jupyterlab_extension/tests/data/ingest-notebook/steps.ipynb
vdk_jupyterlab_extension/vdk_options/__init__.py
vdk_jupyterlab_extension/vdk_options/vdk_options.py
vdk_jupyterlab_extension-0.1.999363461.data/data/etc/jupyter/jupyter_notebook_config.d/vdk-jupyterlab-extension.json
vdk_jupyterlab_extension-0.1.999363461.data/data/etc/jupyter/jupyter_server_config.d/vdk-jupyterlab-extension.json
vdk_jupyterlab_extension-0.1.999363461.data/data/share/jupyter/labextensions/vdk-jupyterlab-extension/package.json
vdk_jupyterlab_extension-0.1.999363461.data/data/share/jupyter/labextensions/vdk-jupyterlab-extension/schemas/vdk-jupyterlab-extension/package.json.orig
vdk_jupyterlab_extension-0.1.999363461.data/data/share/jupyter/labextensions/vdk-jupyterlab-extension/schemas/vdk-jupyterlab-extension/plugin.json
vdk_jupyterlab_extension-0.1.999363461.data/data/share/jupyter/labextensions/vdk-jupyterlab-extension/static/747.f9a85986f2fc01374c58.js
vdk_jupyterlab_extension-0.1.999363461.data/data/share/jupyter/labextensions/vdk-jupyterlab-extension/static/776.b21dba6833c2b31cf334.js
vdk_jupyterlab_extension-0.1.999363461.dist-info/METADATA
vdk_jupyterlab_extension-0.1.999363461.dist-info/WHEEL
vdk_jupyterlab_extension-0.1.999363461.dist-info/licenses/LICENSE
vdk_jupyterlab_extension-0.1.999363461.dist-info/RECORD
