Metadata-Version: 2.1
Name: vdk-jupyterlab-extension
Version: 0.1.999363461
Summary: A Jupyterlab extension for using VDK
Project-URL: Homepage, https://github.com/vmware/versatile-data-kit
Project-URL: Bug Tracker, https://github.com/vmware/versatile-data-kit/issues
Project-URL: Repository, https://github.com/vmware/versatile-data-kit
Author-email: Versatile Data Kit Development Team <versatile-data-kit@vmware.com>
License: See https://github.com/vmware/versatile-data-kit/blob/main/LICENSE
License-File: LICENSE
Classifier: Framework :: Jupyter
Classifier: Framework :: Jupyter :: JupyterLab
Classifier: Framework :: Jupyter :: JupyterLab :: 3
Classifier: Framework :: Jupyter :: JupyterLab :: Extensions
Classifier: Framework :: Jupyter :: JupyterLab :: Extensions :: Prebuilt
Classifier: License :: OSI Approved :: BSD License
Classifier: Programming Language :: Python
Classifier: Programming Language :: Python :: 3
Classifier: Programming Language :: Python :: 3.7
Classifier: Programming Language :: Python :: 3.8
Classifier: Programming Language :: Python :: 3.9
Classifier: Programming Language :: Python :: 3.10
Classifier: Programming Language :: Python :: 3.11
Requires-Python: >=3.7
Requires-Dist: jupyter-server<3,>=1.6
Requires-Dist: jupyterlab==3.6.3
Requires-Dist: vdk-control-cli
Requires-Dist: vdk-core
Provides-Extra: opinionated
Requires-Dist: ipyaggrid; extra == 'opinionated'
Requires-Dist: jupyterlab-execute-time; extra == 'opinionated'
Requires-Dist: lckr-jupyterlab-variableinspector; extra == 'opinionated'
Provides-Extra: test
Requires-Dist: coverage; extra == 'test'
Requires-Dist: httpretty; extra == 'test'
Requires-Dist: pytest; extra == 'test'
Requires-Dist: pytest-asyncio; extra == 'test'
Requires-Dist: pytest-cov; extra == 'test'
Requires-Dist: pytest-jupyter; extra == 'test'
Requires-Dist: pytest-tornasync; extra == 'test'
